platformics/cli/generate_token.py
platformics/cli/main.py
platformics/codegen/.generator.py.swp
platformics/codegen/generator.py
platformics/codegen/lib/linkml_wrappers.py
platformics/codegen/templates/cerbos/config.yaml.j2
platformics/codegen/templates/cerbos/policies/_schemas/principal.json.j2
platformics/codegen/templates/cerbos/policies/class_name.yaml.j2
platformics/codegen/templates/cerbos/policies/derived_roles_common.yaml.j2
platformics/codegen/templates/cerbos/policies/file.yaml.j2
platformics/codegen/templates/database/migrations/env.py.j2
platformics/codegen/templates/database/migrations/script.py.mako.j2
platformics/codegen/templates/database/models/__init__.py.j2
platformics/codegen/templates/database/models/class_name.py.j2
platformics/codegen/templates/graphql_api/helpers/class_name.py.j2
platformics/codegen/templates/graphql_api/mutations.py.j2
platformics/codegen/templates/graphql_api/queries.py.j2
platformics/codegen/templates/graphql_api/types/class_name.py.j2
platformics/codegen/templates/support/enums.py.j2
platformics/codegen/templates/support/limit_offset.py.j2
platformics/codegen/templates/test_infra/factories/class_name.py.j2
platformics/codegen/templates/validators/class_name.py.j2
platformics/database/connect.py
platformics/database/models/__init__.py
platformics/database/models/base.py
platformics/graphql_api/core/deps.py
platformics/graphql_api/core/error_handler.py
platformics/graphql_api/core/errors.py
platformics/graphql_api/core/gql_loaders.py
platformics/graphql_api/core/query_builder.py
platformics/graphql_api/core/query_input_types.py
platformics/graphql_api/core/relay_interface.py
platformics/graphql_api/core/strawberry_extensions.py
platformics/graphql_api/core/strawberry_helpers.py
platformics/graphql_api/relay/__init__.py
platformics/graphql_api/relay/fields.py
platformics/graphql_api/setup.py
platformics/graphql_api/tests/test_hashability.py
platformics/graphql_api/uvicorn_worker.py
platformics/security/authorization.py
platformics-1.0.3.dist-info/LICENSE
platformics-1.0.3.dist-info/METADATA
platformics-1.0.3.dist-info/WHEEL
platformics-1.0.3.dist-info/entry_points.txt
platformics-1.0.3.dist-info/RECORD
