Metadata-Version: 2.1
Name: platformics
Version: 1.0.3
Summary: Codegen Python GraphQL Entity Framework
Home-page: https://github.com/chanzuckerberg/platformics
License: MIT
Keywords: graphql,codegen
Author: CZI Team
Author-email: opensource@chanzuckerberg.com
Requires-Python: >=3.12,<4.0
Classifier: Development Status :: 4 - Beta
Classifier: Intended Audience :: Developers
Classifier: License :: OSI Approved :: MIT License
Classifier: Programming Language :: Python :: 3
Classifier: Programming Language :: Python :: 3.12
Classifier: Topic :: Software Development :: Code Generators
Requires-Dist: alembic (>=1.11.1,<2.0.0)
Requires-Dist: asyncpg (>=0.29.0,<0.30.0)
Requires-Dist: biopython (>=1.84,<2.0)
Requires-Dist: cerbos (>=0.10.0,<0.11.0)
Requires-Dist: fastapi (>=0.115.0,<0.116.0)
Requires-Dist: jinja2 (>=3.1.3,<4.0.0)
Requires-Dist: jwcrypto (>=1.5.6,<2.0.0)
Requires-Dist: linkml (>=1.5.7,<2.0.0)
Requires-Dist: linkml-runtime (>=1.6.0,<2.0.0)
Requires-Dist: psycopg-binary (>=3.1.9,<4.0.0)
Requires-Dist: pydantic (>=2.1.1,<3.0.0)
Requires-Dist: pydantic-settings (>=2.0.2,<3.0.0)
Requires-Dist: sgqlc (>=16.3,<17.0)
Requires-Dist: sqlalchemy_utils (>=0.41.1,<0.42.0)
Requires-Dist: strawberry-graphql (==0.257.0)
Requires-Dist: strcase (>=1.0.0,<2.0.0)
Requires-Dist: types-requests (>=2.31.0.2,<3.0.0.0)
Requires-Dist: uuid6 (>=2023.5.2,<2024.0.0)
Project-URL: Repository, https://github.com/chanzuckerberg/platformics
